{
  "config": {
    "configFile": "C:\\D_Dieu_Disk\\Automation_Practice\\playwright-api-testing\\playwright.config.ts",
    "rootDir": "C:/D_Dieu_Disk/Automation_Practice/playwright-api-testing/tests_ui",
    "forbidOnly": false,
    "fullyParallel": true,
    "globalSetup": null,
    "globalTeardown": null,
    "globalTimeout": 0,
    "grep": {},
    "grepInvert": null,
    "maxFailures": 0,
    "metadata": {
      "actualWorkers": 1
    },
    "preserveOutput": "always",
    "reporter": [
      [
        "dot",
        null
      ],
      [
        "json",
        {
          "outputFile": "JsonReports/jsonReport.json"
        }
      ],
      [
        "html",
        {
          "open": "never"
        }
      ]
    ],
    "reportSlowTests": {
      "max": 5,
      "threshold": 15000
    },
    "quiet": false,
    "projects": [
      {
        "outputDir": "C:/D_Dieu_Disk/Automation_Practice/playwright-api-testing/test-results",
        "repeatEach": 1,
        "retries": 0,
        "id": "chromium",
        "name": "chromium",
        "testDir": "C:/D_Dieu_Disk/Automation_Practice/playwright-api-testing/tests_ui",
        "testIgnore": [],
        "testMatch": [
          "tests_ui/ClientApp.spec.js"
        ],
        "timeout": 30000
      }
    ],
    "shard": null,
    "updateSnapshots": "missing",
    "version": "1.42.1",
    "workers": 6,
    "webServer": null
  },
  "suites": [
    {
      "title": "ClientApp.spec.js",
      "file": "ClientApp.spec.js",
      "column": 0,
      "line": 0,
      "specs": [
        {
          "title": "First Playwright test",
          "ok": true,
          "tags": [],
          "tests": [
            {
              "timeout": 30000,
              "annotations": [],
              "expectedStatus": "passed",
              "projectId": "chromium",
              "projectName": "chromium",
              "results": [
                {
                  "workerIndex": 0,
                  "status": "passed",
                  "duration": 10695,
                  "errors": [],
                  "stdout": [
                    {
                      "text": "[\n  \u001b[32m'ZARA COAT 3'\u001b[39m,\n  \u001b[32m'ADIDAS ORIGINAL'\u001b[39m,\n  \u001b[32m'IPHONE 13 PRO'\u001b[39m,\n  \u001b[32m'Laptop'\u001b[39m,\n  \u001b[32m'Laptop'\u001b[39m,\n  \u001b[32m'Laptop'\u001b[39m,\n  \u001b[32m'Laptop'\u001b[39m,\n  \u001b[32m'Laptop'\u001b[39m,\n  \u001b[32m'Laptop'\u001b[39m\n]\n"
                    },
                    {
                      "text": "\u001b[33m2\u001b[39m\n"
                    },
                    {
                      "text": " | 66152257a86f8f74dcbb5850 | \n"
                    }
                  ],
                  "stderr": [],
                  "retry": 0,
                  "startTime": "2024-04-09T11:11:07.557Z",
                  "attachments": []
                }
              ],
              "status": "expected"
            }
          ],
          "id": "756b2e3d635df17cc925-b9b46dd391fd3f997544",
          "file": "ClientApp.spec.js",
          "line": 4,
          "column": 6
        }
      ]
    }
  ],
  "errors": [],
  "stats": {
    "startTime": "2024-04-09T11:11:07.023Z",
    "duration": 12607.203,
    "expected": 1,
    "skipped": 0,
    "unexpected": 0,
    "flaky": 0
  }
}